baka_i18n/__init__.py
baka_i18n/config.py
baka_i18n/i18n.py
baka_i18n-0.1.3.dist-info/DESCRIPTION.rst
baka_i18n-0.1.3.dist-info/METADATA
baka_i18n-0.1.3.dist-info/RECORD
baka_i18n-0.1.3.dist-info/WHEEL
baka_i18n-0.1.3.dist-info/metadata.json
baka_i18n-0.1.3.dist-info/top_level.txt
